pyModules/__init__.py
pyModules/barPackage/__init__.py
pyModules/barPackage/bar/__init__.py
pyModules/barPackage/bar/barFile.py
pyModules/fooPackage/__init__.py
pyModules/fooPackage/foo/__init__.py
pyModules/fooPackage/foo/fooFile.py
pyModules-0.3.dist-info/DESCRIPTION.rst
pyModules-0.3.dist-info/METADATA
pyModules-0.3.dist-info/RECORD
pyModules-0.3.dist-info/WHEEL
pyModules-0.3.dist-info/entry_points.txt
pyModules-0.3.dist-info/metadata.json
pyModules-0.3.dist-info/top_level.txt
