Metadata-Version: 2.0
Name: pyModules
Version: 0.3
Summary: this is a modules package
Home-page: UNKNOWN
Author: Immo Digital Services
Author-email: team@habiteo.com
License: UNKNOWN
Keywords: modules python packages
Platform: UNKNOWN
Classifier: Development Status :: 7 - Inactive
Classifier: Intended Audience :: Other Audience
Classifier: Topic :: Software Development :: Build Tools
Classifier: License :: Other/Proprietary License
Classifier: Programming Language :: Python :: 3
Classifier: Programming Language :: Python :: 3.3
Classifier: Programming Language :: Python :: 3.4
Classifier: Programming Language :: Python :: 3.5
